[{"data":1,"prerenderedAt":322},["ShallowReactive",2],{"api/page-about-us/stephen-david-bearpark-en":3,"footer-en":55,"navigation-en-default":240,"about-us/stephen-david-bearpark-en-seo":317},{"locale":4,"seo":5,"components":30,"layout":52,"breadcrumbs":53,"geofencings":54},"en",{"title":6,"metaTitle":6,"metaDescription":7,"keywords":8,"metaRobots":8,"structuredData":9,"metaImage":10,"metaSocial":17,"canonicalURL":8,"localizations":18},"About us – Bitstamp","Discover Bitstamp's story, learn about our vision and get to know the people behind the world's longest-standing crypto exchange.",null,{},{"url":11,"mime":12,"ext":13,"width":14,"height":15,"name":16,"alt":8},"bitstampImageUrl/meta_about_us_22ab34a371.png","image/png",".png",1200,630,"meta-about-us.png",[],[19,22,25,28],{"pathname":20,"locale":21},"/en-gb/about-us/stephen-david-bearpark/","en-GB",{"pathname":23,"locale":24},"/sl-si/about-us/stephen-david-bearpark/","sl-SI",{"pathname":26,"locale":27},"/es/about-us/stephen-david-bearpark/","es",{"pathname":29,"locale":4},"/about-us/stephen-david-bearpark/",[31],{"component":32,"name":33,"title":34,"image":35,"biography":43,"ctas":44},"special.team-member","\u003Ch1>Stephen David \u003Cmark>Bearpark\u003C/mark>\u003C/h1>\n","Chief Financial Officer",{"url":36,"mime":37,"ext":38,"width":39,"height":40,"name":41,"alt":42},"bitstampImageUrl/stephen_david_bearpark_f95b4ee5c3.jpg","image/jpeg",".jpg",2000,1332,"stephen-david-bearpark.jpg","Stephen David Bearpark","\u003Cp>With 15 years Finance Leadership experience focused on scaling and transforming businesses in Banking, Consumer Finance, and fast-paced Tech and Fintech environments, Stephen is Bitstamp’s key person for financial expansion across the globe.\u003C/p>\n\u003Cp>Stephen joined Bitstamp from Amazon, where he held the role of Finance Director. Previously he’d gained extensive experience in McKinsey, Provident Mexico, IPF Digital, and Barclays Bank.\u003C/p>\n\u003Cp>He holds a bachelor’s degree in chemistry from the University of Oxford, and qualified as a Chartered Accountant whilst working with PwC.\u003C/p>\n",[45],{"text":46,"url":47,"external":48,"noFollow":48,"type":49,"openModal":8,"downloadItem":50},"Linkedin","https://lu.linkedin.com/in/stephen-bearpark-27aa5b/",true,"Social Link - Linkedin",{"file":51},{},"default",[],{},{"ready":48,"sections":56,"disclaimer":238,"copyright":239},[57,102,125,148,180,199],{"title":58,"content":59,"items":60},"About","",[61,67,72,77,82,87,92,97],{"noFollow":48,"isExternal":62,"name":63,"value":64,"isEmail":62,"isPhoneNumber":62,"isText":62,"showOnDesktop":48,"showOnMobile":48,"attachment":65,"geofencings":66},false,"Who We Are","/about-us/",{},{},{"noFollow":62,"isExternal":62,"name":68,"value":69,"isEmail":62,"isPhoneNumber":62,"isText":62,"showOnDesktop":48,"showOnMobile":48,"attachment":70,"geofencings":71},"The Bitstamp Way","/bitstamp-way/",{},{},{"noFollow":48,"isExternal":48,"name":73,"value":74,"isEmail":62,"isPhoneNumber":62,"isText":62,"showOnDesktop":48,"showOnMobile":48,"attachment":75,"geofencings":76},"Careers","https://bitstamp.workable.com/",{},{},{"noFollow":48,"isExternal":62,"name":78,"value":79,"isEmail":62,"isPhoneNumber":62,"isText":62,"showOnDesktop":48,"showOnMobile":48,"attachment":80,"geofencings":81},"Legal & Privacy","/legal/",{},{},{"noFollow":48,"isExternal":62,"name":83,"value":84,"isEmail":62,"isPhoneNumber":62,"isText":62,"showOnDesktop":48,"showOnMobile":48,"attachment":85,"geofencings":86},"Legal & Privacy - USA","/legal/terms-of-use/inc/",{},{},{"noFollow":48,"isExternal":62,"name":88,"value":89,"isEmail":62,"isPhoneNumber":62,"isText":62,"showOnDesktop":48,"showOnMobile":48,"attachment":90,"geofencings":91},"For Law Enforcement","/legal/guidelines-for-law-enforcement-agencies/",{},{},{"noFollow":48,"isExternal":62,"name":93,"value":94,"isEmail":62,"isPhoneNumber":62,"isText":62,"showOnDesktop":48,"showOnMobile":48,"attachment":95,"geofencings":96},"Fee Schedule","/fee-schedule/",{},{},{"noFollow":62,"isExternal":62,"name":98,"value":99,"isEmail":62,"isPhoneNumber":62,"isText":62,"showOnDesktop":48,"showOnMobile":48,"attachment":100,"geofencings":101},"FAQ","/faq/",{},{},{"title":103,"content":59,"items":104},"Products",[105,110,115,120],{"noFollow":62,"isExternal":62,"name":106,"value":107,"isEmail":62,"isPhoneNumber":62,"isText":62,"showOnDesktop":48,"showOnMobile":48,"attachment":108,"geofencings":109},"Mobile App","/mobile/",{},{},{"noFollow":62,"isExternal":62,"name":111,"value":112,"isEmail":62,"isPhoneNumber":62,"isText":62,"showOnDesktop":48,"showOnMobile":48,"attachment":113,"geofencings":114},"Tradeview","/market/tradeview/",{},{},{"noFollow":62,"isExternal":62,"name":116,"value":117,"isEmail":62,"isPhoneNumber":62,"isText":62,"showOnDesktop":48,"showOnMobile":48,"attachment":118,"geofencings":119},"Earn Stake","/crypto-staking/",{},{"geofencing-uk":48},{"noFollow":62,"isExternal":62,"name":121,"value":122,"isEmail":62,"isPhoneNumber":62,"isText":62,"showOnDesktop":48,"showOnMobile":48,"attachment":123,"geofencings":124},"Earn Lend","/crypto-lending/",{},{"geofencing-uk":48},{"title":126,"content":59,"items":127},"Services",[128,133,138,143],{"noFollow":62,"isExternal":62,"name":129,"value":130,"isEmail":62,"isPhoneNumber":62,"isText":62,"showOnDesktop":48,"showOnMobile":48,"attachment":131,"geofencings":132},"Institutions & Partners","/institutional-trading/",{},{},{"noFollow":62,"isExternal":62,"name":134,"value":135,"isEmail":62,"isPhoneNumber":62,"isText":62,"showOnDesktop":48,"showOnMobile":48,"attachment":136,"geofencings":137},"Bitstamp as a Service","/bitstamp-as-a-service/",{},{},{"noFollow":62,"isExternal":62,"name":139,"value":140,"isEmail":62,"isPhoneNumber":62,"isText":62,"showOnDesktop":48,"showOnMobile":48,"attachment":141,"geofencings":142},"The Bitstamp Ecosystem","/partners/",{},{},{"noFollow":62,"isExternal":62,"name":144,"value":145,"isEmail":62,"isPhoneNumber":62,"isText":62,"showOnDesktop":48,"showOnMobile":48,"attachment":146,"geofencings":147},"Pro","/pro/",{},{},{"title":149,"content":59,"items":150},"Resources",[151,156,161,166,170,175],{"noFollow":48,"isExternal":62,"name":152,"value":153,"isEmail":62,"isPhoneNumber":62,"isText":62,"showOnDesktop":62,"showOnMobile":48,"attachment":154,"geofencings":155},"HTTP API","/api/",{},{},{"noFollow":62,"isExternal":62,"name":157,"value":158,"isEmail":62,"isPhoneNumber":62,"isText":62,"showOnDesktop":62,"showOnMobile":48,"attachment":159,"geofencings":160},"Websocket API v2","/websocket/v2/",{},{},{"noFollow":62,"isExternal":62,"name":162,"value":163,"isEmail":62,"isPhoneNumber":62,"isText":62,"showOnDesktop":62,"showOnMobile":48,"attachment":164,"geofencings":165},"FIX v2","/fix/v2/",{},{},{"noFollow":48,"isExternal":62,"name":167,"value":153,"isEmail":62,"isPhoneNumber":62,"isText":62,"showOnDesktop":48,"showOnMobile":62,"attachment":168,"geofencings":169},"API Documentation",{},{},{"noFollow":62,"isExternal":62,"name":171,"value":172,"isEmail":62,"isPhoneNumber":62,"isText":62,"showOnDesktop":48,"showOnMobile":48,"attachment":173,"geofencings":174},"PGP Key","/pgp-key/",{},{},{"noFollow":62,"isExternal":62,"name":176,"value":177,"isEmail":62,"isPhoneNumber":62,"isText":62,"showOnDesktop":48,"showOnMobile":48,"attachment":178,"geofencings":179},"Lightning Network","/lightning-network-node/",{},{},{"title":181,"content":59,"items":182},"Address",[183,187,191,195],{"noFollow":62,"isExternal":62,"name":184,"value":59,"isEmail":62,"isPhoneNumber":62,"isText":48,"showOnDesktop":48,"showOnMobile":48,"attachment":185,"geofencings":186},"Bitstamp Ltd",{},{},{"noFollow":62,"isExternal":62,"name":188,"value":59,"isEmail":62,"isPhoneNumber":62,"isText":48,"showOnDesktop":48,"showOnMobile":48,"attachment":189,"geofencings":190},"5 New Street Square",{},{},{"noFollow":62,"isExternal":62,"name":192,"value":59,"isEmail":62,"isPhoneNumber":62,"isText":48,"showOnDesktop":48,"showOnMobile":48,"attachment":193,"geofencings":194},"London, EC4A 3TW",{},{},{"noFollow":62,"isExternal":62,"name":196,"value":59,"isEmail":62,"isPhoneNumber":62,"isText":48,"showOnDesktop":48,"showOnMobile":48,"attachment":197,"geofencings":198},"United Kingdom",{},{},{"title":200,"content":59,"items":201},"Contact",[202,207,211,215,219,223,228,233],{"noFollow":62,"isExternal":62,"name":203,"value":204,"isEmail":62,"isPhoneNumber":62,"isText":62,"showOnDesktop":48,"showOnMobile":48,"attachment":205,"geofencings":206},"Customer support","/customer-support/",{},{},{"noFollow":62,"isExternal":62,"name":208,"value":208,"isEmail":48,"isPhoneNumber":62,"isText":62,"showOnDesktop":48,"showOnMobile":48,"attachment":209,"geofencings":210},"info@bitstamp.net",{},{},{"noFollow":62,"isExternal":62,"name":212,"value":212,"isEmail":48,"isPhoneNumber":62,"isText":62,"showOnDesktop":48,"showOnMobile":48,"attachment":213,"geofencings":214},"press@bitstamp.net",{},{},{"noFollow":62,"isExternal":62,"name":216,"value":216,"isEmail":48,"isPhoneNumber":62,"isText":62,"showOnDesktop":48,"showOnMobile":48,"attachment":217,"geofencings":218},"support@bitstamp.net",{},{},{"noFollow":62,"isExternal":62,"name":220,"value":220,"isEmail":48,"isPhoneNumber":62,"isText":62,"showOnDesktop":48,"showOnMobile":48,"attachment":221,"geofencings":222},"complaints@bitstamp.net",{},{},{"noFollow":62,"isExternal":62,"name":224,"value":225,"isEmail":62,"isPhoneNumber":48,"isText":62,"showOnDesktop":48,"showOnMobile":48,"attachment":226,"geofencings":227},"+44 20 3868 9628","+442038689628",{},{},{"noFollow":62,"isExternal":62,"name":229,"value":230,"isEmail":62,"isPhoneNumber":48,"isText":62,"showOnDesktop":48,"showOnMobile":48,"attachment":231,"geofencings":232},"+1 800 712 5702","+18007125702",{},{},{"noFollow":62,"isExternal":62,"name":234,"value":235,"isEmail":62,"isPhoneNumber":48,"isText":62,"showOnDesktop":48,"showOnMobile":48,"attachment":236,"geofencings":237},"+352 20 88 10 96","+35220881096",{},{},"\u003Cp>Bitstamp USA, Inc. is licensed to engage in Virtual Currency Business Activity by the New York State Department of Financial Services. Licensed as a Money Transmitter by the New York State Department of Financial Services.\u003C/p>\n","\u003Cp>All rights reserved © 2025 Bitstamp. \u003Ca href=\"https://www.nmlsconsumeraccess.org/EntityDetails.aspx/COMPANY/1905429\" target=\"_blank\" rel=\"noopener noreferrer nofollow\">NMLS #1905429\u003C/a>\u003C/p>\n",{"items":241,"ready":48,"platformButtonText":313,"backButtonText":314,"logInButtonText":315,"signUpButtonText":316},[242,246,249,252,255,258,263,266,271,309],{"headerName":243,"sidemenuName":129,"url":130,"noFollow":62,"showInHeader":48,"showInSidemenu":48,"geofencings":244,"submenu":245},"Institutions",{},[],{"headerName":144,"sidemenuName":144,"url":145,"noFollow":62,"showInHeader":48,"showInSidemenu":48,"geofencings":247,"submenu":248},{},[],{"headerName":106,"sidemenuName":106,"url":107,"noFollow":62,"showInHeader":48,"showInSidemenu":48,"geofencings":250,"submenu":251},{},[],{"headerName":116,"sidemenuName":116,"url":117,"noFollow":62,"showInHeader":48,"showInSidemenu":48,"geofencings":253,"submenu":254},{"geofencing-uk":48},[],{"headerName":121,"sidemenuName":121,"url":122,"noFollow":62,"showInHeader":48,"showInSidemenu":48,"geofencings":256,"submenu":257},{"geofencing-uk":48},[],{"headerName":259,"sidemenuName":259,"url":260,"noFollow":62,"showInHeader":48,"showInSidemenu":48,"geofencings":261,"submenu":262},"Markets","/markets/",{},[],{"headerName":111,"sidemenuName":111,"url":112,"noFollow":62,"showInHeader":48,"showInSidemenu":48,"geofencings":264,"submenu":265},{},[],{"headerName":267,"sidemenuName":267,"url":268,"noFollow":62,"showInHeader":48,"showInSidemenu":48,"geofencings":269,"submenu":270},"Blog","https://blog.bitstamp.net/",{},[],{"headerName":272,"sidemenuName":272,"url":273,"noFollow":62,"showInHeader":48,"showInSidemenu":48,"geofencings":274,"submenu":275},"Learn","/learn/",{},[276,279,282,285,288,291,294,297,300,303,306],{"title":277,"url":278,"noFollow":62},"Bitstamp tutorials","/learn/bitstamp-tutorials/",{"title":280,"url":281,"noFollow":62},"Blockchain technology","/learn/blockchain/",{"title":283,"url":284,"noFollow":62},"Company profiles","/learn/company-profiles/",{"title":286,"url":287,"noFollow":62},"Crypto 101","/learn/crypto-101/",{"title":289,"url":290,"noFollow":62},"Crypto definitions","/learn/crypto-definitions/",{"title":292,"url":293,"noFollow":62},"Crypto trading","/learn/crypto-trading/",{"title":295,"url":296,"noFollow":62},"Crypto categories","/crypto-categories/",{"title":298,"url":299,"noFollow":62},"Cryptocurrency guide","/learn/cryptocurrency-guide/",{"title":301,"url":302,"noFollow":62},"People profiles","/learn/people-profiles/",{"title":304,"url":305,"noFollow":62},"Security","/learn/security/",{"title":307,"url":308,"noFollow":62},"Web3","/learn/web3/",{"headerName":310,"sidemenuName":310,"url":107,"noFollow":62,"showInHeader":62,"showInSidemenu":48,"geofencings":311,"submenu":312},"Get Bitstamp app",{},[],"Go to platform","Back","Log in","Get started",{"description":7,"ogDescription":7,"ogImage":318,"twitterImage":318,"twitterSite":319,"twitterCreator":319,"twitterCard":320,"twitterTitle":6,"twitterDescription":7,"titleTemplate":321},"https://assets.bitstamp.net/msc/_ipx/enlarge_true&f_png&fit_cover&q_85&s_1200x630/bitstampImageUrl/meta_about_us_22ab34a371.png","@Bitstamp","summary_large_image","%s",1739277379783]