{"name":"Tether","symbol":"USDT","id":3,"guid":"1e3a8ea7-0d4f-4060-85a4-11b22f2d91b5","hideMarketCap":false,"sentiment":[{"date":"2025-01-13","telegram":{"neutral":6,"negative":0,"positive":16},"twitter":{"neutral":0,"negative":0,"positive":0}},{"date":"2025-01-14","telegram":{"neutral":9,"negative":0,"positive":7},"twitter":{"neutral":0,"negative":0,"positive":0}},{"date":"2025-01-15","telegram":{"neutral":15,"negative":1,"positive":13},"twitter":{"neutral":0,"negative":0,"positive":0}},{"date":"2025-01-16","telegram":{"neutral":12,"negative":0,"positive":7},"twitter":{"neutral":0,"negative":0,"positive":0}},{"date":"2025-01-17","telegram":{"neutral":6,"negative":1,"positive":6},"twitter":{"neutral":0,"negative":0,"positive":0}},{"date":"2025-01-18","telegram":{"neutral":6,"negative":0,"positive":19},"twitter":{"neutral":0,"negative":0,"positive":0}},{"date":"2025-01-19","telegram":{"neutral":18,"negative":0,"positive":2},"twitter":{"neutral":0,"negative":0,"positive":0}},{"date":"2025-01-20","telegram":{"neutral":14,"negative":1,"positive":8},"twitter":{"neutral":0,"negative":0,"positive":0}},{"date":"2025-01-21","telegram":{"neutral":10,"negative":1,"positive":12},"twitter":{"neutral":0,"negative":0,"positive":0}},{"date":"2025-01-22","telegram":{"neutral":17,"negative":0,"positive":4},"twitter":{"neutral":0,"negative":0,"positive":0}},{"date":"2025-01-23","telegram":{"neutral":43,"negative":2,"positive":7},"twitter":{"neutral":0,"negative":0,"positive":0}},{"date":"2025-01-24","telegram":{"neutral":18,"negative":1,"positive":3},"twitter":{"neutral":0,"negative":0,"positive":0}},{"date":"2025-01-25","telegram":{"neutral":11,"negative":1,"positive":5},"twitter":{"neutral":0,"negative":0,"positive":0}},{"date":"2025-01-26","telegram":{"neutral":11,"negative":0,"positive":8},"twitter":{"neutral":0,"negative":0,"positive":0}},{"date":"2025-01-27","telegram":{"neutral":16,"negative":0,"positive":25},"twitter":{"neutral":0,"negative":0,"positive":0}},{"date":"2025-01-28","telegram":{"neutral":10,"negative":1,"positive":8},"twitter":{"neutral":0,"negative":0,"positive":0}},{"date":"2025-01-29","telegram":{"neutral":10,"negative":0,"positive":5},"twitter":{"neutral":0,"negative":0,"positive":0}},{"date":"2025-01-30","telegram":{"neutral":22,"negative":1,"positive":14},"twitter":{"neutral":0,"negative":0,"positive":0}},{"date":"2025-01-31","telegram":{"neutral":21,"negative":2,"positive":11},"twitter":{"neutral":0,"negative":0,"positive":0}},{"date":"2025-02-01","telegram":{"neutral":16,"negative":2,"positive":5},"twitter":{"neutral":0,"negative":0,"positive":0}},{"date":"2025-02-02","telegram":{"neutral":18,"negative":0,"positive":6},"twitter":{"neutral":0,"negative":0,"positive":0}},{"date":"2025-02-03","telegram":{"neutral":12,"negative":0,"positive":8},"twitter":{"neutral":0,"negative":0,"positive":0}},{"date":"2025-02-04","telegram":{"neutral":11,"negative":2,"positive":9},"twitter":{"neutral":0,"negative":0,"positive":0}},{"date":"2025-02-05","telegram":{"neutral":14,"negative":0,"positive":8},"twitter":{"neutral":0,"negative":0,"positive":0}},{"date":"2025-02-06","telegram":{"neutral":23,"negative":0,"positive":11},"twitter":{"neutral":0,"negative":0,"positive":0}},{"date":"2025-02-07","telegram":{"neutral":13,"negative":0,"positive":23},"twitter":{"neutral":0,"negative":0,"positive":0}},{"date":"2025-02-08","telegram":{"neutral":8,"negative":0,"positive":8},"twitter":{"neutral":0,"negative":0,"positive":0}},{"date":"2025-02-09","telegram":{"neutral":15,"negative":2,"positive":47},"twitter":{"neutral":0,"negative":0,"positive":0}},{"date":"2025-02-10","telegram":{"neutral":22,"negative":0,"positive":11},"twitter":{"neutral":0,"negative":0,"positive":0}},{"date":"2025-02-11","telegram":{"neutral":19,"negative":0,"positive":11},"twitter":{"neutral":0,"negative":0,"positive":0}},{"date":"2025-02-12","telegram":{"neutral":22,"negative":2,"positive":19},"twitter":{"neutral":0,"negative":0,"positive":0}}]}